ai_debugger_inc-0.1.2.dist-info/licenses/LICENSE
aidb/__init__.py
aidb/adapters/__init__.py
aidb/adapters/constants.py
aidb/adapters/base/__init__.py
aidb/adapters/base/adapter.py
aidb/adapters/base/compilation_patterns.py
aidb/adapters/base/config.py
aidb/adapters/base/config_mapper.py
aidb/adapters/base/hooks.py
aidb/adapters/base/initialize.py
aidb/adapters/base/launch.py
aidb/adapters/base/source_path_resolver.py
aidb/adapters/base/subprocess_validator.py
aidb/adapters/base/syntax_validator.py
aidb/adapters/base/target_classifier.py
aidb/adapters/base/target_resolver.py
aidb/adapters/base/vscode_variables.py
aidb/adapters/base/vslaunch.py
aidb/adapters/base/components/__init__.py
aidb/adapters/base/components/launch_orchestrator.py
aidb/adapters/base/components/port_manager.py
aidb/adapters/base/components/process_manager.py
aidb/adapters/downloader/__init__.py
aidb/adapters/downloader/download.py
aidb/adapters/downloader/result.py
aidb/adapters/downloader/version.py
aidb/adapters/lang/__init__.py
aidb/adapters/lang/java/__init__.py
aidb/adapters/lang/java/compilation.py
aidb/adapters/lang/java/config.py
aidb/adapters/lang/java/java.py
aidb/adapters/lang/java/jdtls_project_pool.py
aidb/adapters/lang/java/source_detection.py
aidb/adapters/lang/java/source_path_resolver.py
aidb/adapters/lang/java/syntax_validator.py
aidb/adapters/lang/java/target_resolver.py
aidb/adapters/lang/java/hooks/__init__.py
aidb/adapters/lang/java/hooks/lifecycle_hooks.py
aidb/adapters/lang/java/lsp/__init__.py
aidb/adapters/lang/java/lsp/bridge_cleanup.py
aidb/adapters/lang/java/lsp/debug_session_manager.py
aidb/adapters/lang/java/lsp/jdtls_process_manager.py
aidb/adapters/lang/java/lsp/lsp_bridge.py
aidb/adapters/lang/java/lsp/lsp_client.py
aidb/adapters/lang/java/lsp/lsp_initialization.py
aidb/adapters/lang/java/lsp/lsp_message_handler.py
aidb/adapters/lang/java/lsp/lsp_protocol.py
aidb/adapters/lang/java/lsp/workspace_manager.py
aidb/adapters/lang/java/tooling/__init__.py
aidb/adapters/lang/java/tooling/build_system_detector.py
ai_debugger_inc-0.1.2.dist-info/METADATA
ai_debugger_inc-0.1.2.dist-info/WHEEL
ai_debugger_inc-0.1.2.dist-info/entry_points.txt
ai_debugger_inc-0.1.2.dist-info/top_level.txt
ai_debugger_inc-0.1.2.dist-info/RECORD
