Metadata-Version: 2.4
Name: ai-debugger-inc
Version: 0.1.2
Summary: A lightweight Python API that enables AI systems to
Author-email: AI Debugger <info@ai-debugger.com>
License:                                  Apache License
Project-URL: Homepage, https://github.com/ai-debugger-inc/aidb
Project-URL: Documentation, https://ai-debugger.com
Project-URL: Issue Tracker, https://github.com/ai-debugger-inc/aidb/issues
Keywords: AI Debugger,aidb,debugging
Classifier: License :: OSI Approved :: Apache Software License
Classifier: Development Status :: 4 - Beta
Classifier: Intended Audience :: Developers
Classifier: Programming Language :: Python :: 3
Classifier: Programming Language :: Python :: 3.10
Classifier: Programming Language :: Python :: 3.11
Classifier: Programming Language :: Python :: 3.12
Classifier: Topic :: Software Development :: Debuggers
Classifier: Operating System :: MacOS
Classifier: Operating System :: POSIX :: Linux
Requires-Python: >=3.10
License-File: LICENSE
Requires-Dist: aiofiles<26.0.0,>=23.0.0
Requires-Dist: mcp<2.0.0,>=1.0.0
Requires-Dist: psutil<8.0.0,>=5.9.0
Provides-Extra: dev
Requires-Dist: click<9.0.0,>=8.0.0; extra == "dev"
Requires-Dist: jinja2<4.0.0,>=3.1.0; extra == "dev"
Requires-Dist: requests<3.0.0,>=2.32.2; extra == "dev"
Requires-Dist: tiktoken<1.0.0,>=0.8.0; extra == "dev"
Requires-Dist: docformatter<2.0.0,>=1.7.0; extra == "dev"
Requires-Dist: mdformat<2.0.0,>=0.7.0; extra == "dev"
Requires-Dist: mypy<2.0.0,>=1.18.2; extra == "dev"
Requires-Dist: pydocstyle<7.0.0,>=6.3.0; extra == "dev"
Requires-Dist: ruff<1.0.0,>=0.14.4; extra == "dev"
Requires-Dist: bandit<2.0.0,>=1.8.6; extra == "dev"
Requires-Dist: deptry<1.0.0,>=0.24.0; extra == "dev"
Requires-Dist: safety<4.0.0,>=3.7.0; extra == "dev"
Requires-Dist: vulture<3.0,>=2.14; extra == "dev"
Requires-Dist: anthropic<1.0.0,>=0.45.0; extra == "dev"
Requires-Dist: pre-commit<5.0.0,>=4.4.0; extra == "dev"
Requires-Dist: python-dotenv<2.0.0,>=1.2.1; extra == "dev"
Requires-Dist: pyyaml<8.0,>=6.0; extra == "dev"
Requires-Dist: tomli<3.0.0,>=2.3.0; extra == "dev"
Requires-Dist: yamllint<2.0.0,>=1.37.1; extra == "dev"
Requires-Dist: types-aiofiles<26.0.0,>=25.1.0; extra == "dev"
Requires-Dist: types-docutils<1.0.0,>=0.21.0; extra == "dev"
Requires-Dist: types-PyYAML<7.0.0,>=6.0.0; extra == "dev"
Requires-Dist: types-requests<3.0.0,>=2.32.0; extra == "dev"
Requires-Dist: types-setuptools<81.0.0,>=80.9.0; extra == "dev"
Requires-Dist: build<2.0.0,>=1.3.0; extra == "dev"
Requires-Dist: setuptools<81.0.0,>=80.9.0; extra == "dev"
Requires-Dist: wheel<1.0.0,>=0.45.1; extra == "dev"
Provides-Extra: ci-validation
Requires-Dist: aiofiles<26.0.0,>=24.1.0; extra == "ci-validation"
Requires-Dist: click<9.0.0,>=8.0.0; extra == "ci-validation"
Requires-Dist: jinja2<4.0.0,>=3.1.6; extra == "ci-validation"
Requires-Dist: psutil<8.0.0,>=7.0.0; extra == "ci-validation"
Requires-Dist: pyyaml<8.0,>=6.0; extra == "ci-validation"
Provides-Extra: docs
Requires-Dist: linkify-it-py<3.0.0,>=2.0.3; extra == "docs"
Requires-Dist: myst_parser<5.0.0,>=4.0.1; extra == "docs"
Requires-Dist: pydata-sphinx-theme<1.0.0,>=0.16.1; extra == "docs"
Requires-Dist: sphinx<9.0.0,>=8.2.3; extra == "docs"
Requires-Dist: sphinx-autoapi<4.0.0,>=3.0.0; extra == "docs"
Requires-Dist: sphinx-click<7.0.0,>=6.0.0; extra == "docs"
Requires-Dist: sphinx-copybutton<1.0.0,>=0.5.2; extra == "docs"
Requires-Dist: sphinx-design<1.0.0,>=0.6.1; extra == "docs"
Requires-Dist: sphinx-favicon<2.0.0,>=1.0.1; extra == "docs"
Requires-Dist: sphinxcontrib-mermaid<3.0.0,>=1.0.0; extra == "docs"
Requires-Dist: tomli<3.0.0,>=2.3.0; python_version < "3.11" and extra == "docs"
Provides-Extra: test
Requires-Dist: coverage<8.0.0,>=7.11.2; extra == "test"
Requires-Dist: docker<8.0.0,>=7.1.0; extra == "test"
Requires-Dist: python-dotenv<2.0.0,>=1.2.1; extra == "test"
Requires-Dist: pytest<10.0.0,>=8.2.0; extra == "test"
Requires-Dist: pytest-asyncio<2.0.0,>=1.2.0; extra == "test"
Requires-Dist: pytest-cov<8.0.0,>=7.0.0; extra == "test"
Requires-Dist: pytest-mock<4.0.0,>=3.15.1; extra == "test"
Requires-Dist: pytest-rerunfailures<17.0,>=16.1; extra == "test"
Requires-Dist: pytest-timeout<3.0.0,>=2.4.0; extra == "test"
Requires-Dist: pytest-xdist<4.0.0,>=3.8.0; extra == "test"
Requires-Dist: responses<1.0.0,>=0.25.8; extra == "test"
Dynamic: license-file
